calendar/__init__.py
calendar/helpers.py
calendar/wm_week.py
walmartcalendar-1.1.0.dist-info/METADATA
walmartcalendar-1.1.0.dist-info/RECORD
walmartcalendar-1.1.0.dist-info/WHEEL
walmartcalendar-1.1.0.dist-info/top_level.txt
