Metadata-Version: 2.1
Name: walmartcalendar
Version: 1.1.0
Summary: Micro library for performing data calculations with Walmart's 4-5-4 retail calendar
Home-page: https://github.com/merchantlabs/walmart-calendar
Author: Merchant Labs
Author-email: support@merchantlabs.io
License: MIT
Keywords: data-analytics calendar bi
Platform: UNKNOWN
Classifier: Development Status :: 3 - Alpha
Classifier: Intended Audience :: Developers
Classifier: Topic :: Software Development :: Build Tools
Classifier: License :: OSI Approved :: MIT License
Classifier: Programming Language :: Python :: 2
Classifier: Programming Language :: Python :: 3
Provides-Extra: test
Provides-Extra: test
Requires-Dist: pytest; extra == 'test'
